{
  "chainId": 43114,
  "address": "0xab592d197ACc575D16C3346f4EB70C703F308D1E",
  "decimals": 18,
  "name": "chikn feed",
  "symbol": "FEED",
  "contractType": "ERC-20",
  "resourceLinks": [],
  "logoUri": "https://raw.githubusercontent.com/pangolindex/tokens/main/assets/0xab592d197ACc575D16C3346f4EB70C703F308D1E/logo.png",
  "description": "chikn are not just NFTs that lay $egg.\r\nchikn is an entire ecosystem built around these NFTs - encompassing novel Tri-Token Architecture.\r\nchikn is extending the utility of Public Minting, a Marketplace, and Farming for emerging NFT+token creators on Avalanche.\r\n\r\nNFTs have the unique ability to combine utility with the power of mimetism.\r\nWhen you can have both, why not have both?\r\n\r\nIt's simple, really. Everyone knows that chikn lay $egg."
}
